{
  "btn": {
    "spaceing": {
      "0": {
        "$type": "dimension",
        "$value": "0.25rem"
      },
      "1": {
        "$type": "dimension",
        "$value": "0.275rem"
      }
    },
    "color": {
      "$type": "color",
      "$value": "#EBEBEB"
    }
  },
  "secundary": {
    "spaceing": {
      "0": {
        "$type": "dimension",
        "$value": "0.575rem"
      },
      "1": {
        "$type": "dimension",
        "$value": "1.25rem"
      }
    },
    "color": {
      "$type": "color",
      "$value": "#FFD43B"
    }
  },
  "outlined": {
    "border": {
      "$type": "border",
      "$value": "#F2F2F2"
    },
    "spaceing": {
      "0": {
        "$type": "dimension",
        "$value": "0.575rem"
      },
      "1": {
        "$type": "dimension",
        "$value": "1.25rem"
      }
    }
  }
}
